download_esm/__init__.py
download_esm/__main__.py
download_esm/cli.py
download_esm-0.1a0.dist-info/LICENSE
download_esm-0.1a0.dist-info/METADATA
download_esm-0.1a0.dist-info/WHEEL
download_esm-0.1a0.dist-info/entry_points.txt
download_esm-0.1a0.dist-info/top_level.txt
download_esm-0.1a0.dist-info/RECORD
