Metadata-Version: 2.1
Name: download-esm
Version: 0.1a0
Summary: Download ESM modules from npm and jsdelivr
Home-page: https://github.com/simonw/download-esm
Author: Simon Willison
License: Apache License, Version 2.0
Project-URL: Issues, https://github.com/simonw/download-esm/issues
Project-URL: CI, https://github.com/simonw/download-esm/actions
Project-URL: Changelog, https://github.com/simonw/download-esm/releases
Requires-Python: >=3.7
License-File: LICENSE
Requires-Dist: click
Requires-Dist: httpx
Provides-Extra: test
Requires-Dist: pytest ; extra == 'test'
Requires-Dist: pytest-httpx ; extra == 'test'
